LICENSE
License.txt
README.md
setup.py
nerdler_tc/__init__.py
nerdler_tc/text_cleaner.py
nerdler_tc.egg-info/PKG-INFO
nerdler_tc.egg-info/SOURCES.txt
nerdler_tc.egg-info/dependency_links.txt
nerdler_tc.egg-info/top_level.txt