Metadata-Version: 2.1
Name: nerdler-tc
Version: 1.0.0
Summary: Clean text from special characters and blanks
Home-page: https://www.nerdler.pt
Author: nerdler_pt
Author-email: no-reply@nerdler.pt
License: MIT
Platform: any
License-File: LICENSE
License-File: License.txt
